Workbook

Sheet 00_README
A1: 🌶️ CHILLI FARM MANAGEMENT WORKBOOK
A3: Mapped to 9-Domain Success Framework | Cili Kulai Polybag | Malaysia
A5: HOW TO USE
A6: 1 | B6: Start on sheet 01_DASHBOARD — enter farm name, cycle dates, plant count.
A7: 2 | B7: Use 02_DAILY_CHECKLIST every morning (15 min). Mark Status: Done / Issue.
A8: 3 | B8: Use 03_WEEKLY_CHECKLIST once per week (Sunday recommended).
A9: 4 | B9: Use 04_CYCLE_CHECKLIST at each crop stage gate (sow → transplant → harvest).
A10: 5 | B10: Log data in sheets 05–10 as events happen (water, pests, harvest, sales).
A11: 6 | B11: Review 01_DASHBOARD monthly — update KPIs and financial summary.
A12: 7 | B12: Use 11_SCALING_ROADMAP when ready to expand beyond baseline.
A13: 8 | B13: Sheet 12_MASTER_INDEX lists every item in the 9×9 framework.
A15: TIP | B15: Duplicate this file per crop cycle: Chilli_Cycle1_2026.xlsx
A16: TIP | B16: Red 'Issue' status = action needed before next checklist.
A17: TIP | B17: Targets are for ~50–200 polybag home/small farm. Adjust in Dashboard.
A22: SHEET INDEX
A23: Sheet | B23: Purpose
A24: 01_DASHBOARD | B24: KPI summary, targets, financial snapshot
A25: 02_DAILY_CHECKLIST | B25: Daily farm operations (9 domains)
A26: 03_WEEKLY_CHECKLIST | B26: Weekly reviews and deeper checks
A27: 04_CYCLE_CHECKLIST | B27: Stage-gate tasks: nursery → harvest → reset
A28: 05_PRODUCTION | B28: Variety, density, growth stage tracker
A29: 06_FINANCIALS | B29: CAPEX, OPEX, cost/kg, profit, ROI
A30: 07_WATER_FERTILIZER | B30: EC, pH, volume, feed log
A31: 08_PEST_DISEASE | B31: Scouting, ID, treatment, loss
A32: 09_HARVEST_QUALITY | B32: Pick log, grading, rejects
A33: 10_MARKET_SALES | B33: Buyers, price, quantity, revenue
A34: 11_SCALING_ROADMAP | B34: Start small → prove profit → expand
A35: 12_MASTER_INDEX | B35: Full 9-domain framework reference

Sheet 01_DASHBOARD
A1: FARM KPI DASHBOARD
A3: Field | B3: Value
A4: Farm / Operator
A5: Location
A6: Variety | B6: Cili Kulai
A7: Cycle # | B7: 1
A8: Cycle Start (sow date)
A9: Transplant Date
A10: Target Harvest Start
A11: Number of Polybags | B11: 100
A12: Plants Alive (current)
A13: Polybag Size (L) | B13: 7
A14: Saleable Yield Target (kg)
A15: Sale Price Target (RM/kg) | B15: 12
A18: LIVE KPIs (auto-calculated where linked)
A19: KPI | B19: Target | C19: Actual | D19: Status
A20: Plant survival rate (%) | B20: ≥90% | C20: =IF(B8=0,"",IFERROR(B9/B8*100,""))
A21: Saleable yield (kg total) | B21: =B12 | C21: =SUM('09_HARVEST_QUALITY'!J:J)
A22: Yield per plant (kg) | B22: 0.8–1.5 | C22: =IF(B9=0,"",IFERROR(SUM('09_HARVEST_QUALITY'!J:J)/B9,""))
A23: Total revenue (RM) | C23: =SUM('10_MARKET_SALES'!G:G)
A24: Total OPEX (RM) | C24: =SUM('06_FINANCIALS'!E:E)
A25: Total CAPEX (RM) | C25: =SUMIF('06_FINANCIALS'!C:C,"CAPEX",'06_FINANCIALS'!E:E)
A26: Cost per kg (RM) | B26: <8 | C26: =IF(SUM('09_HARVEST_QUALITY'!J:J)=0,"",IFERROR(SUM('06_FINANCIALS'!E:E)/SUM('09_HARVEST_QUALITY'!J:J),""))
A27: Cost per plant (RM) | C27: =IF(B9=0,"",IFERROR(SUM('06_FINANCIALS'!E:E)/B9,""))
A28: Gross profit (RM) | B28: >0 | C28: =IFERROR(SUM('10_MARKET_SALES'!G:G)-SUM('06_FINANCIALS'!E:E),"")
A29: Break-even kg | C29: =IF(B13=0,"",IFERROR(SUM('06_FINANCIALS'!E:E)/B13,""))
A30: Reject rate (%) | B30: <10% | C30: =IF(SUM('09_HARVEST_QUALITY'!I:I)=0,"",IFERROR(SUM('09_HARVEST_QUALITY'!K:K)/SUM('09_HARVEST_QUALITY'!I:I)*100,""))
A31: Pest/disease loss (%) | B31: <5%
A34: 9-DOMAIN HEALTH SCORE (manual weekly 1–5)
A35: Domain | B35: Score (1–5) | C35: Notes
A36: 1. Production
A37: 2. Financials
A38: 3. Farm Management
A39: 4. Water & Fertilizer
A40: 5. Pest & Disease
A41: 6. Harvest & Quality
A42: 7. Market & Sales
A43: 8. Data & Technology
A44: 9. Scaling

Sheet 02_DAILY_CHECKLIST
A1: DAILY CHECKLIST (≈15 min)
A2: Date: ___________ Operator: ___________ Weather: ___________
A4: # | B4: Domain | C4: Category | D4: Task / Check | E4: Target / Standard | F4: Actual / Reading | G4: Status | H4: Notes / Action
A5: 1 | B5: 3. Farm Management | C5: Daily checklist | D5: Walk all bags — note wilt, yellowing, pests | E5: All bags checked | G5: Pending
A6: 2 | B6: 3. Farm Management | C6: Irrigation | D6: Finger-test media 3 cm deep; water if dry | E6: No waterlogging | G6: Pending
A7: 3 | B7: 4. Water & Fertilizer | C7: Volume | D7: Record total water/fertigation per bag (ml) | E7: Per stage target | G7: Pending
A8: 4 | B8: 4. Water & Fertilizer | C8: EC | D8: Check feed EC if fertigating (leachate sample) | E8: 1.2–2.5 mS/cm | G8: Pending
A9: 5 | B9: 4. Water & Fertilizer | C9: pH | D9: Check feed pH if meter available | E9: 5.5–6.5 | G9: Pending
A10: 6 | B10: 5. Pest & Disease | C10: Scouting | D10: Check leaf undersides, new growth, fruit | E10: <5% plants affected | G10: Pending
A11: 7 | B11: 5. Pest & Disease | C11: Detection | D11: Log any aphids, thrips, mites, snails | E11: Record in sheet 08 | G11: Pending
A12: 8 | B12: 1. Production | C12: Growth | D12: Note plant height/stage anomalies | E12: Uniform growth | G12: Pending
A13: 9 | B13: 6. Harvest & Quality | C13: Harvest | D13: Pick mature fruit (green or red per market) | E13: Every 1–2 days in peak | G13: Pending
A14: 10 | B14: 6. Harvest & Quality | C14: Rejects | D14: Separate damaged/rotten fruit — do not mix | E14: Reject bin separate | G14: Pending
A15: 11 | B15: 8. Data & Technology | C15: Records | D15: Log harvest kg, water, issues in log sheets | E15: Same day entry | G15: Pending
A16: 12 | B16: 3. Farm Management | C16: Maintenance | D16: Check stakes, drippers, shade net, drainage | E16: No blocked drippers | G16: Pending
... A18: 14 | B18: 2. Financials | C18: Cash flow | D18: Record any purchases or sales today (RM) | E18: Logged in sheet 06/10 | G18: Pending

Sheet 03_WEEKLY_CHECKLIST
A1: WEEKLY CHECKLIST (≈1 hour)
A2: Date: ___________ Operator: ___________ Weather: ___________
A4: # | B4: Domain | C4: Category | D4: Task / Check | E4: Target / Standard | F4: Actual / Reading | G4: Status | H4: Notes / Action
A5: 1 | B5: 4. Water & Fertilizer | C5: Salt flush | D5: Plain water flush 15–20% leachate all bags | E5: Once per week | G5: Pending
A6: 2 | B6: 4. Water & Fertilizer | C6: Fertilizer | D6: Side-dress or adjust fertigation EC per stage | E6: Per schedule | G6: Pending
A7: 3 | B7: 5. Pest & Disease | C7: Prevention | D7: Yellow sticky traps check / replace | E7: Traps clean | G7: Pending
A8: 4 | B8: 5. Pest & Disease | C8: Monitoring | D8: Calculate % plants with pest/disease | E8: <5% threshold | G8: Pending
A9: 5 | B9: 5. Pest & Disease | C9: Sanitation | D9: Remove dead leaves, fallen fruit, weeds | E9: Clean aisles | G9: Pending
A10: 6 | B10: 1. Production | C10: Plant density | D10: Confirm 1 plant/bag; remove volunteers | E10: 1 plant per bag | G10: Pending
A11: 7 | B11: 1. Production | C11: Flowering/Fruit set | D11: Count flowers and small fruit per sample plant | E11: 10 sample plants | G11: Pending
A12: 8 | B12: 3. Farm Management | C12: SOP | D12: Review any deviations from SOP this week | E12: Document fixes | G12: Pending
A13: 9 | B13: 6. Harvest & Quality | C13: Grading | D13: Review grade mix — adjust picking timing | E13: Grade A >70% | G13: Pending
A14: 10 | B14: 6. Harvest & Quality | C14: Loss reduction | D14: Calculate weekly reject % | E14: <10% | G14: Pending
A15: 11 | B15: 7. Market & Sales | C15: Buyers | D15: Contact buyers for next week's demand | E15: 1+ buyer confirmed | G15: Pending
A16: 12 | B16: 7. Market & Sales | C16: Price | D16: Check market price (wet market/wholesale) | E16: Logged | G16: Pending
... A22: 18 | B22: 3. Farm Management | C22: Records | D22: Backup notebook / photos / spreadsheet | E22: Weekly backup | G22: Pending

Sheet 04_CYCLE_CHECKLIST
A1: CROP CYCLE CHECKLIST (sow → harvest → reset)
A2: Date: ___________ Operator: ___________ Weather: ___________
A4: # | B4: Domain | C4: Category | D4: Task / Check | E4: Target / Standard | F4: Actual / Reading | G4: Status | H4: Notes / Action
A5: 1 | B5: 9. Scaling | C5: Start small | D5: Define cycle size (# bags) and budget cap | E5: Written plan | G5: Pending
A6: 2 | B6: 9. Scaling | C6: Baseline | D6: Record starting media, seed lot, costs | E6: Sheet 05/06 | G6: Pending
A7: 3 | B7: 2. Financials | C7: CAPEX | D7: List all one-time purchases (bags, drip, net) | E7: Sheet 06 | G7: Pending
A8: 4 | B8: 2. Financials | C8: OPEX | D8: Budget seeds, media, fertiliser, labour | E8: Sheet 06 | G8: Pending
A9: 5 | B9: 1. Production | C9: Variety | D9: Label all seed lots; record germination % | E9: >70% germination | G9: Pending
A10: 6 | B10: 1. Production | C10: Nursery | D10: Seed treatment (captan); sow 0.5 cm depth | E10: DOA protocol | G10: Pending
A11: 7 | B11: 1. Production | C11: Nursery | D11: Seedling mix: 60–70% cocopeat + 30–40% compost | E11: pH 5.5–6.5 | G11: Pending
A12: 8 | B12: 4. Water & Fertilizer | C12: Water quality | D12: Use clean water; note source (tap/bore/rain) | E12: No contamination | G12: Pending
A13: 9 | B13: 1. Production | C13: Nursery | D13: Week 2 foliar feed (½ strength) | E13: Once only | G13: Pending
A14: 10 | B14: 1. Production | C14: Nursery | D14: Seedlings 4–6 true leaves, 15–25 cm | E14: Week 4–6 | G14: Pending
A15: 11 | B15: 3. Farm Management | C15: SOP | D15: Harden seedlings 5–7 days before transplant | E15: Mandatory | G15: Pending
A16: 12 | B16: 1. Production | C16: Transplanting | D16: Transplant late afternoon; 7 L horizontal bag | E16: Same depth as seedling | G16: Pending
... A45: 41 | B45: 9. Scaling | C45: SOP | D45: Update SOP with lessons learned | E45: Version +1 | G45: Pending

Sheet 05_PRODUCTION
A1: PRODUCTION TRACKER
A3: Plant ID / Bag # | B3: Variety | C3: Seed Lot | D3: Sow Date | E3: Germ % | F3: Transplant Date | G3: Bag Size (L) | H3: Media Mix | I3: Growth Stage | J3: Height (cm) | K3: Flowering Date | L3: First Harvest | M3: Total Yield (kg) | N3: Saleable (kg) | O3: Notes | P3: Experiment Tag
A4: 1
A5: 2
A6: 3
A7: 4
A8: 5
A9: 6
A10: 7
A11: 8
A12: 9
A13: 10
A14: 11
A15: 12
... A53: 50

Sheet 06_FINANCIALS
A1: FINANCIAL TRACKER (CAPEX + OPEX)
A3: Date | B3: Category | C3: Type | D3: Item | E3: Amount (RM) | F3: Qty | G3: Unit Cost | H3: Payment Method | I3: Notes
B4: Equipment | C4: CAPEX | D4: Drip irrigation kit | E4: 350
B5: Equipment | C5: CAPEX | D5: EC/pH meter | E5: 80
B6: Equipment | C6: CAPEX | D6: Shade net 30% | E6: 200
B7: Seeds | C7: OPEX | D7: Kulai F1 seed 10g | E7: 25
B8: Media | C8: OPEX | D8: Cocopeat 5kg × 20 | E8: 120
B9: Media | C9: OPEX | D9: Compost 50kg | E9: 40
B10: Fertiliser | C10: OPEX | D10: NPK 12:12:17 25kg | E10: 55
B11: Packaging | C11: OPEX | D11: Plastic crates | E11: 30
B12: Labour | C12: OPEX | D12: Transplanting (own) | E12: 0

Sheet 07_WATER_FERTILIZER
A1: WATER & FERTILIZER LOG
A2: *DAT = Days After Transplant
A3: Date | B3: Time | C3: Bag #/Zone | D3: Method | E3: Water (ml) | F3: Fertiliser Used | G3: EC (mS/cm) | H3: pH | I3: Leachate EC | J3: Weather | K3: DAT* | L3: Stage | M3: Notes

Sheet 08_PEST_DISEASE
A1: PEST & DISEASE LOG
A3: Date | B3: Bag #/Zone | C3: Type | D3: Pest/Disease Name | E3: Severity (1-5) | F3: % Plants Affected | G3: Identification Method | H3: Treatment Applied | I3: TDMH Date | J3: Outcome | K3: Loss (kg or plants) | L3: Sanitation Done? | M3: SOP Ref | N3: Recovery Notes

Sheet 09_HARVEST_QUALITY
A1: HARVEST & QUALITY LOG
A3: Date | B3: Bag #/Zone | C3: Pick # | D3: Maturity | E3: Grade A (kg) | F3: Grade B (kg) | G3: Grade C (kg) | H3: Total Picked (kg) | I3: Saleable (kg) | J3: Reject (kg) | K3: Reject Reason | L3: Storage Location | M3: Hours to Sale | N3: Notes
H4: =SUM(E4:G4) | I4: =E4+F4 | J4: =G4
H5: =SUM(E5:G5) | I5: =E5+F5 | J5: =G5
H6: =SUM(E6:G6) | I6: =E6+F6 | J6: =G6
H7: =SUM(E7:G7) | I7: =E7+F7 | J7: =G7
H8: =SUM(E8:G8) | I8: =E8+F8 | J8: =G8
H9: =SUM(E9:G9) | I9: =E9+F9 | J9: =G9
H10: =SUM(E10:G10) | I10: =E10+F10 | J10: =G10
H11: =SUM(E11:G11) | I11: =E11+F11 | J11: =G11
H12: =SUM(E12:G12) | I12: =E12+F12 | J12: =G12
H13: =SUM(E13:G13) | I13: =E13+F13 | J13: =G13

Sheet 10_MARKET_SALES
A1: MARKET & SALES LOG
A3: Date | B3: Buyer Type | C3: Buyer Name | D3: Channel | E3: Grade | F3: Qty (kg) | G3: Price (RM/kg) | H3: Revenue (RM) | I3: Quality Feedback | J3: Payment Status | K3: Notes
H4: =F4*G4
H5: =F5*G5
H6: =F6*G6
H7: =F7*G7
H8: =F8*G8
H9: =F9*G9
H10: =F10*G10
H11: =F11*G11
H12: =F12*G12
H13: =F13*G13
H14: =F14*G14
H15: =F15*G15
... H53: =F53*G53

Sheet 11_SCALING_ROADMAP
A1: SCALING ROADMAP — Start Small → Prove Profit → Expand
A3: Phase | B3: Step | C3: Action | D3: Success Criteria | E3: Status | F3: Date Done | G3: Notes
A4: Phase 0 | B4: Start small | C4: 10–20 bags pilot | D4: Learn without big loss | E4: Pending
A5: Phase 1 | B5: Baseline | C5: Record all costs & yields | D5: Know true cost/kg | E5: Pending
A6: Phase 2 | B6: Measure | C6: Track survival, yield, reject % | D6: KPIs in Dashboard | E6: Pending
A7: Phase 3 | B7: Improve | C7: Fix top 3 problems | D7: SOP updated | E7: Pending
A8: Phase 4 | B8: Repeat | C8: Run cycle 2 at 50 bags | D8: Compare to cycle 1 | E8: Pending
A9: Phase 5 | B9: Prove profit | C9: Profit > 0 for 2 cycles | D9: RM/plant documented | E9: Pending
A10: Phase 6 | B10: SOP | C10: Write 1-page SOP per task | D10: Train helper | E10: Pending
A11: Phase 7 | B11: Expand | C11: 100 → 200 bags | D11: Only if survival >90% | E11: Pending
A12: Phase 8 | B12: Replicate | C12: Second site or partner farm | D12: Same SOP, same results | E12: Pending

Sheet 12_MASTER_INDEX
A1: 9-DOMAIN MASTER INDEX — Every goal mapped to sheet & action
A3: Domain | B3: Goal / Topic | C3: Sheet | D3: Frequency | E3: Key Target (Kulai polybag) | F3: Linked KPI
A4: 1. Production | B4: Variety | C4: 05_PRODUCTION | D4: Per cycle | E4: Kulai / hybrid — label all lots | F4: Germ %
A5: 1. Production | B5: Plant density | C5: 05_PRODUCTION | D5: Transplant | E5: 1 plant / 7 L bag, 45–60 cm spacing | F5: Survival %
A6: 1. Production | B6: Nursery | C6: 04_CYCLE + 05 | D6: Week 0–6 | E6: 4–6 true leaves before transplant | F6: Germ >70%
A7: 1. Production | B7: Transplanting | C7: 04_CYCLE | D7: Week 6 | E7: Late PM, shade 5–7 days | F7: Survival >90%
A8: 1. Production | B8: Growth | C8: 02_DAILY + 05 | D8: Daily/weekly | E8: Stake by week 4–5 post-transplant | F8: Height 70–80 cm
A9: 1. Production | B9: Flowering | C9: 05_PRODUCTION | D9: Week 8–10 | E9: Log first flower date | F9: Flower drop <30%
A10: 1. Production | B10: Fruit set | C10: 05_PRODUCTION | D10: Weekly | E10: Monitor small fruit count | F10: Fruit/plant
A11: 1. Production | B11: Yield | C11: 09_HARVEST | D11: Per pick | E11: Track cumulative kg | F11: 0.8–1.5 kg/plant
A12: 1. Production | B12: Saleable yield | C12: 09_HARVEST | D12: Per pick | E12: Total − rejects | F12: >90% saleable
A13: 2. Financials | B13: CAPEX | C13: 06_FINANCIALS | D13: Per cycle | E13: Equipment, infrastructure | F13: Total CAPEX
A14: 2. Financials | B14: OPEX | C14: 06_FINANCIALS | D14: Ongoing | E14: Seeds, media, feed, labour | F14: Total OPEX
... A84: 9. Scaling | B84: Replicate | C84: 11_SCALING | D84: Phase 8 | E84: New site/partner | F84: Same results
